<?xml version="1.0" encoding="UTF-8" ?>
<XMLDB PATH="local/iomadcustompage/db" VERSION="20240417" COMMENT="XMLDB file for Moodle local/iomadcustompage"
    xmlns:xsi="http://www.w3.org/2001/XMLSchema-instance"
    xsi:noNamespaceSchemaLocation="../../../lib/xmldb/xmldb.xsd"
>
  <TABLES>
    <TABLE NAME="local_iomadcustompages" COMMENT="Table to keep track and their details of custom pages">
      <FIELDS>
        <FIELD NAME="id" TYPE="int" LENGTH="10" NOTNULL="true" SEQUENCE="true"/>
        <FIELD NAME="name" TYPE="char" LENGTH="150" NOTNULL="true" SEQUENCE="false"/>
        <FIELD NAME="title" TYPE="char" LENGTH="50" NOTNULL="false" SEQUENCE="false" COMMENT="title to show in navigation, if null name field will be used"/>
        <FIELD NAME="contextid" TYPE="int" LENGTH="10" NOTNULL="false" SEQUENCE="false"/>
        <FIELD NAME="parent" TYPE="int" LENGTH="10" NOTNULL="false" SEQUENCE="false" COMMENT="parent page of this page"/>
        <FIELD NAME="usercreated" TYPE="int" LENGTH="10" NOTNULL="true" SEQUENCE="false"/>
        <FIELD NAME="usermodified" TYPE="int" LENGTH="10" NOTNULL="true" DEFAULT="0" SEQUENCE="false"/>
        <FIELD NAME="timecreated" TYPE="int" LENGTH="10" NOTNULL="true" SEQUENCE="false"/>
        <FIELD NAME="timemodified" TYPE="int" LENGTH="10" NOTNULL="false" SEQUENCE="false"/>
      </FIELDS>
      <KEYS>
        <KEY NAME="primary" TYPE="primary" FIELDS="id"/>
      </KEYS>
      <INDEXES>
        <INDEX NAME="iomadcustompage_par_ix" UNIQUE="false" FIELDS="parent"/>
        <INDEX NAME="cuspage_use_ix" UNIQUE="false" FIELDS="usercreated"/>
        <INDEX NAME="cuspage_use2_ix" UNIQUE="false" FIELDS="usermodified"/>
        <INDEX NAME="cuspage_con_ix" UNIQUE="false" FIELDS="contextid"/>
      </INDEXES>
    </TABLE>
    <TABLE NAME="local_iomadcustompage_audience" COMMENT="iomadcustompage_audience table retrofitted from MySQL">
      <FIELDS>
        <FIELD NAME="id" TYPE="int" LENGTH="19" NOTNULL="true" SEQUENCE="true"/>
        <FIELD NAME="pageid" TYPE="int" LENGTH="10" NOTNULL="true" SEQUENCE="false"/>
        <FIELD NAME="heading" TYPE="char" LENGTH="255" NOTNULL="false" SEQUENCE="false"/>
        <FIELD NAME="classname" TYPE="char" LENGTH="255" NOTNULL="true" SEQUENCE="false"/>
        <FIELD NAME="configdata" TYPE="text" NOTNULL="true" SEQUENCE="false"/>
        <FIELD NAME="usercreated" TYPE="int" LENGTH="19" NOTNULL="true" DEFAULT="0" SEQUENCE="false"/>
        <FIELD NAME="usermodified" TYPE="int" LENGTH="19" NOTNULL="true" DEFAULT="0" SEQUENCE="false"/>
        <FIELD NAME="timecreated" TYPE="int" LENGTH="19" NOTNULL="true" DEFAULT="0" SEQUENCE="false"/>
        <FIELD NAME="timemodified" TYPE="int" LENGTH="19" NOTNULL="true" DEFAULT="0" SEQUENCE="false"/>
      </FIELDS>
      <KEYS>
        <KEY NAME="primary" TYPE="primary" FIELDS="id"/>
      </KEYS>
      <INDEXES>
        <INDEX NAME="cuspageaudi_page_ix" UNIQUE="false" FIELDS="pageid"/>
        <INDEX NAME="cuspageaudi_use_ix" UNIQUE="false" FIELDS="usercreated"/>
        <INDEX NAME="cuspageaudi_use2_ix" UNIQUE="false" FIELDS="usermodified"/>
      </INDEXES>
    </TABLE>
  </TABLES>
</XMLDB>
